{
  "repos": [
    {
      "alias": "tesseract", 
      "repos_name": "tesseract", 
      "tags": [
        "cpp", 
        "cmake", 
        "travis", 
        "asciidoc", 
        "docker", 
        "docker_compose", 
        "tesseract"
      ], 
      "user": "tesseract-ocr"
    }, 
    {
      "alias": "tess4j", 
      "repos_name": "tess4j", 
      "tags": ["tesseract", "java"], 
      "user": "nguyenq"
    }, 
    {
      "alias": "zsh", 
      "repos_name": "zsh", 
      "tags": ["c", "autotools", "zsh"], 
      "user": "zsh-users"
    }, 
    {
      "alias": "sqlite", 
      "repos_name": "sqlite", 
      "tags": ["c", "autotools", "sqlite"], 
      "user": "mackyle"
    }, 
    {
      "alias": "openssh", 
      "repos_name": "openssh", 
      "tags": ["c", "autotools", "ssh"], 
      "user": "antonyantony"
    }, 
    {
      "alias": "tmux", 
      "repos_name": "tmux", 
      "tags": ["c", "autotools", "tmux"], 
      "user": "tmux"
    }, 
    {
      "alias": "postgres", 
      "repos_name": "postgres", 
      "tags": ["c", "autotools", "postgres"], 
      "user": "postgres"
    }, 
    {
      "alias": "Paddle", 
      "repos_name": "Paddle", 
      "tags": ["c", "cmake", "deep_learning"], 
      "user": "PaddlePaddle"
    }, 
    {
      "alias": "mysql-server", 
      "repos_name": "mysql-server", 
      "tags": ["c", "cmake", "mysql"], 
      "user": "mysql"
    }, 
    {
      "alias": "ccls", 
      "repos_name": "ccls", 
      "tags": ["cpp", "cmake", "cpp_tool", "vim"], 
      "user": "MaskRay"
    }, 
    {
      "alias": "impala", 
      "repos_name": "impala", 
      "tags": ["c", "cmake", "impala"], 
      "user": "apache"
    }, 
    {
      "alias": "redis", 
      "repos_name": "redis", 
      "tags": ["c", "make", "redis"], 
      "user": "antirez"
    }, 
    {
      "alias": "git", 
      "repos_name": "git", 
      "tags": ["c", "make", "git"], 
      "user": "git"
    }, 
    {
      "alias": "vim", 
      "repos_name": "vim", 
      "tags": ["c", "make", "vim"], 
      "user": "vim"
    }, 
    {
      "alias": "docker-pdi-ce", 
      "repos_name": "docker-pdi-ce", 
      "tags": ["docker_compose", "kettle"], 
      "user": "zhicwu"
    }, 
    {
      "alias": "pentaho-kettle", 
      "repos_name": "pentaho-kettle", 
      "tags": ["java", "kettle"], 
      "user": "pentaho"
    }, 
    {
      "alias": "docker-gpdb5", 
      "repos_name": "gpdb5", 
      "tags": ["docker", "greenplum"], 
      "user": "bbotev01"
    }, 
    {
      "alias": "gpdb-ansible", 
      "repos_name": "gpdb-ansible", 
      "tags": ["ansible", "greenplum"], 
      "user": "andreasscherbaum"
    }, 
    {
      "alias": "greenplum-ansible", 
      "repos_name": "greenplum", 
      "tags": ["ansible", "greenplum"], 
      "user": "faer615"
    }, 
    {
      "alias": "gpdb", 
      "repos_name": "gpdb", 
      "tags": ["greenplum", "c"], 
      "user": "greenplum-db"
    }, 
    {
      "alias": "ansible.pentaho-biserver-ce", 
      "repos_name": "ansible.pentaho-biserver-ce", 
      "score": 2, 
      "tags": ["docker_compose", "pentaho"], 
      "user": "oggers"
    }, 
    {
      "alias": "kylin", 
      "repos_name": "kylin", 
      "tags": ["java", "kylin"], 
      "user": "apache"
    }, 
    {
      "alias": "envelope", 
      "repos_name": "envelope", 
      "tags": ["java", "envelope", "spark"], 
      "user": "cloudera-labs"
    }, 
    {
      "alias": "kettle-manager", 
      "repos_name": "kettle-manager", 
      "score": 2, 
      "tags": ["java", "webui", "kettle"], 
      "user": "majinju"
    }, 
    {
      "alias": "webkettle", 
      "repos_name": "webkettle", 
      "tags": ["java", "docker_compose", "webui", "kettle"], 
      "user": "JoeyBling"
    }, 
    {
      "alias": "generator-jhipster", 
      "repos_name": "generator-jhipster", 
      "tags": ["javascript", "jhipster"], 
      "user": "jhipster"
    }, 
    {
      "alias": "jhipster-uml", 
      "repos_name": "jhipster-uml", 
      "tags": ["javascript", "jhipster"], 
      "user": "jhipster"
    }, 
    {
      "alias": "lb-2-jhipster", 
      "repos_name": "lb-2-jhipster", 
      "tags": ["javascript", "jhipster"], 
      "user": "ziogiugno"
    }, 
    {
      "alias": "SpringCloud", 
      "repos_name": "SpringCloud", 
      "tags": ["java", "docker_compose", "springcloud"], 
      "user": "zhoutaoo"
    }, 
    {
      "alias": "apollo-build-scripts", 
      "repos_name": "apollo-build-scripts", 
      "tags": ["docker_compose", "apollo"], 
      "user": "nobodyiam"
    }, 
    {
      "alias": "docker-tomcat", 
      "repos_name": "tomcat", 
      "score": 2, 
      "tags": ["docker", "tomcat"], 
      "user": "docker-library"
    }, 
    {
      "alias": "docker-mysql", 
      "repos_name": "mysql", 
      "tags": ["docker", "mysql"], 
      "user": "docker-library"
    }, 
    {
      "alias": "docker-tomcat8", 
      "repos_name": "docker-tomcat8", 
      "tags": ["docker", "tomcat"], 
      "user": "cmoro-deusto"
    }, 
    {
      "alias": "f2etest", 
      "repos_name": "f2etest", 
      "tags": ["f2etest"], 
      "user": "alibaba"
    }, 
    {
      "alias": "kylin-docker", 
      "repos_name": "kylin-docker", 
      "tags": ["docker", "kylin"], 
      "user": "Kyligence"
    }, 
    {
      "alias": "ssb-kylin", 
      "repos_name": "ssb-kylin", 
      "tags": ["kylin"], 
      "user": "Kyligence"
    }, 
    {
      "alias": "kylin-tpch", 
      "repos_name": "kylin-tpch", 
      "tags": ["kylin"], 
      "user": "Kyligence"
    }, 
    {
      "alias": "kylin-archetype", 
      "repos_name": "kylin-archetype", 
      "tags": ["kylin", "maven", "archetype"], 
      "user": "wengyingjian"
    }, 
    {
      "alias": "big-data-olap", 
      "repos_name": "big-data-olap", 
      "tags": ["kylin"], 
      "user": "okmich"
    }, 
    {
      "alias": "hadoop-docker", 
      "repos_name": "hadoop-docker", 
      "tags": ["docker", "hadoop"], 
      "user": "sequenceiq"
    }, 
    {
      "alias": "hadoop-ansible", 
      "repos_name": "hadoop-ansible", 
      "tags": ["ansible", "hadoop"], 
      "user": "analytically"
    }, 
    {
      "alias": "hadoop-kerberos-helm", 
      "repos_name": "hadoop-kerberos-helm", 
      "tags": ["helm", "kubernetes", "hadoop"], 
      "user": "ifilonenko"
    }, 
    {
      "alias": "kubespray", 
      "repos_name": "kubespray", 
      "tags": ["kubernetes", "ansible"], 
      "user": "kubernetes-sigs"
    }, 
    {
      "alias": "kubekit", 
      "repos_name": "kubekit", 
      "tags": ["kubernetes"], 
      "user": "Orientsoft"
    }, 
    {
      "alias": "ansible-playbooks-cdh5", 
      "repos_name": "ansible-playbooks-cdh5", 
      "tags": ["ansible", "cdh"], 
      "user": "mcsrainbow"
    }, 
    {
      "alias": "ansible-playbooks-cdh6", 
      "repos_name": "ansible-playbooks-cdh6", 
      "tags": ["ansible", "cdh"], 
      "user": "bjddd192"
    }, 
    {
      "alias": "spark-knn_graphs", 
      "repos_name": "spark-knn_graphs", 
      "tags": ["spark", "knn_graph"], 
      "user": "tdebatty"
    }, 
    {
      "alias": "cypher-for-apache-spark", 
      "repos_name": "cypher-for-apache-spark", 
      "tags": ["spark", "cypher"], 
      "user": "opencypher"
    }, 
    {
      "alias": "mizo", 
      "repos_name": "mizo", 
      "tags": ["spark", "titan"], 
      "user": "imri"
    }, 
    {
      "alias": "spark-neo4j", 
      "repos_name": "spark-neo4j", 
      "tags": ["spark", "neo4j"], 
      "user": "kbastani"
    }, 
    {
      "alias": "neo4j-mazerunner", 
      "repos_name": "neo4j-mazerunner", 
      "tags": ["neo4j", "mazerunner", "spark"], 
      "user": "neo4j-contrib"
    }, 
    {
      "alias": "camel", 
      "repos_name": "camel", 
      "tags": ["camel", "asciidoc"], 
      "user": "apache"
    }, 
    {
      "alias": "docker-postgres", 
      "repos_name": "postgres", 
      "tags": ["docker", "postgres"], 
      "user": "docker-library"
    }, 
    {
      "alias": "docker-postgresql", 
      "repos_name": "docker-postgresql", 
      "tags": ["docker", "postgres"], 
      "user": "sameersbn"
    }, 
    {
      "alias": "DataX", 
      "repos_name": "DataX", 
      "tags": ["datax"], 
      "user": "alibaba"
    }, 
    {
      "alias": "datax-web", 
      "repos_name": "datax-web", 
      "tags": ["datax"], 
      "user": "zipingdong"
    }, 
    {
      "alias": "flinkx", 
      "repos_name": "flinkx", 
      "tags": ["flink", "flinkx"], 
      "user": "DTStack"
    }, 
    {
      "alias": "flinkStreamSQL", 
      "repos_name": "flinkStreamSQL", 
      "tags": ["flink"], 
      "user": "DTStack"
    }, 
    {
      "alias": "ClickHouse", 
      "repos_name": "ClickHouse", 
      "tags": ["clickhouse"], 
      "user": "yandex"
    }, 
    {
      "alias": "mondrian", 
      "repos_name": "mondrian", 
      "tags": ["mandrian"], 
      "user": "pentaho"
    }, 
    {
      "alias": "Agriculture_KnowledgeGraph", 
      "repos_name": "Agriculture_KnowledgeGraph", 
      "tags": ["agriculture_knowledge_graph"], 
      "user": "hejack0207"
    }, 
    {
      "alias": "Agriculture-KnowledgeGraph-Data", 
      "repos_name": "Agriculture-KnowledgeGraph-Data", 
      "tags": ["agriculture_knowledge_graph"], 
      "user": "CrisJk"
    }, 
    {
      "alias": "orientdb", 
      "repos_name": "orientdb", 
      "tags": ["orientdb"], 
      "user": "orientechnologies"
    }, 
    {
      "alias": "plantuml", 
      "repos_name": "plantuml", 
      "tags": ["plantuml"], 
      "user": "plantuml"
    }, 
    {
      "alias": "jsonnet", 
      "repos_name": "jsonnet", 
      "tags": ["jsonnet"], 
      "user": "google"
    }, 
    {
      "alias": "spark-jobserver", 
      "repos_name": "spark-jobserver", 
      "tags": ["spark", "restful"], 
      "user": "spark-jobserver"
    }, 
    {
      "alias": "ngx-graph", 
      "repos_name": "ngx-graph", 
      "tags": ["angular", "graph_ui"], 
      "user": "swimlane"
    }, 
    {
      "alias": "servicemix-docker", 
      "repos_name": "servicemix-docker", 
      "tags": ["servicemix", "docker"], 
      "user": "mzipay"
    }, 
    {
      "alias": "mkroli-servicemix-docker", 
      "repos_name": "servicemix-docker", 
      "tags": ["servicemix", "docker"], 
      "user": "mkroli"
    }, 
    {
      "alias": "pdi-cluster", 
      "repos_name": "pdi-cluster", 
      "tags": ["kettle"], 
      "user": "zhicwu"
    }, 
    {
      "alias": "flink", 
      "repos_name": "flink", 
      "tags": ["flink"], 
      "user": "apache"
    }, 
    {
      "alias": "ImpalaGIS", 
      "repos_name": "ImpalaGIS", 
      "tags": ["impalagis", "impala"], 
      "user": "fzn0268"
    }, 
    {
      "alias": "graphdb-benchmarks", 
      "repos_name": "graphdb-benchmarks", 
      "tags": ["benchmark"], 
      "user": "socialsensor"
    }, 
    {
      "alias": "angular2-swagger-apiclient-generator", 
      "repos_name": "angular2-swagger-apiclient-generator", 
      "tags": ["angular", "swagger", "swagger_angular"], 
      "user": "zemacik"
    }, 
    {
      "alias": "ng-swagger-gen", 
      "repos_name": "ng-swagger-gen", 
      "tags": ["angular", "swagger", "swagger_angular"], 
      "user": "cyclosproject"
    }, 
    {
      "alias": "SparkGIS", 
      "repos_name": "SparkGIS", 
      "tags": ["spark", "sparkgis"], 
      "user": "drubbo"
    }, 
    {
      "alias": "EasyOCR", 
      "repos_name": "EasyOCR", 
      "tags": ["ocr_impl"], 
      "user": "ushelp"
    }, 
    {
      "alias": "OCR", 
      "repos_name": "OCR", 
      "tags": ["ocr_impl"], 
      "user": "zoso10"
    }, 
    {
      "alias": "Longan", 
      "repos_name": "Longan", 
      "tags": ["ocr_impl"], 
      "user": "Zarkonnen"
    }, 
    {
      "alias": "NewOCR", 
      "repos_name": "NewOCR", 
      "tags": ["ocr_impl"], 
      "user": "RubbaBoy"
    }, 
    {
      "alias": "SequoiaDB", 
      "repos_name": "SequoiaDB", 
      "tags": ["cpp"], 
      "user": "SequoiaDB"
    }, 
    {
      "alias": "learn_kylin", 
      "repos_name": "learn_kylin", 
      "tags": ["kylin"], 
      "user": "Kyligence"
    }, 
    {
      "alias": "Movie_Recommend", 
      "repos_name": "Movie_Recommend", 
      "tags": ["spark", "bigdata_usecase"], 
      "user": "LuckyZXL2016"
    }, 
    {
      "alias": "spark-deep-learning", 
      "repos_name": "spark-deep-learning", 
      "tags": ["spark", "deep_learning"], 
      "user": "databricks"
    }, 
    {
      "alias": "SparkInternals", 
      "repos_name": "SparkInternals", 
      "tags": ["spark"], 
      "user": "JerryLead"
    }, 
    {
      "alias": "docker-presto", 
      "repos_name": "docker-presto", 
      "tags": ["docker", "presto"], 
      "user": "zhicwu"
    }, 
    {
      "alias": "incubator-doris", 
      "repos_name": "incubator-doris", 
      "tags": ["mpp_based", "sql_support", "datawarehouse_impl"], 
      "user": "apache"
    }, 
    {
      "alias": "incubator-pinot", 
      "repos_name": "incubator-pinot", 
      "tags": ["olap_impl", "pinot"], 
      "user": "apache"
    }, 
    {
      "alias": "drill", 
      "repos_name": "drill", 
      "tags": ["mpp_based", "sql_support", "hadoop", "drill"], 
      "user": "apache"
    }, 
    {
      "alias": "awesome-ocr", 
      "repos_name": "awesome-ocr", 
      "tags": ["ocr_awesome"], 
      "user": "kba"
    }, 
    {
      "alias": "QGIS", 
      "repos_name": "QGIS", 
      "tags": ["gis_impl"], 
      "user": "qgis"
    }, 
    {
      "alias": "csirt", 
      "repos_name": "csirt", 
      "tags": ["security_awesome"], 
      "user": "Spacial"
    }, 
    {
      "alias": "awesome-web-security", 
      "repos_name": "awesome-web-security", 
      "tags": ["websecurity_awesome"], 
      "user": "qazbnm456"
    }, 
    {
      "alias": "awesome-cve-poc", 
      "repos_name": "awesome-cve-poc", 
      "tags": ["security_cve"], 
      "user": "qazbnm456"
    }, 
    {
      "alias": "keepalived", 
      "repos_name": "keepalived", 
      "tags": ["keepalived"], 
      "user": "acassen"
    }, 
    {
      "alias": "ansible-role-drill", 
      "repos_name": "ansible-role-drill", 
      "tags": ["ansible", "drill"], 
      "user": "futuresystems"
    }, 
    {
      "alias": "awesome-bigdata", 
      "repos_name": "awesome-bigdata", 
      "tags": ["bigdata_awesome"], 
      "user": "onurakpolat"
    }, 
    {
      "alias": "awesome-pipline", 
      "repos_name": "awesome-pipline", 
      "tags": ["etl_awesome"], 
      "user": "pditommaso"
    }, 
    {
      "alias": "awesome-etl", 
      "repos_name": "awesome-etl", 
      "tags": ["etl_awesome"], 
      "user": "pawl"
    }, 
    {
      "alias": "json-to-plantuml", 
      "repos_name": "json-to-plantuml", 
      "tags": ["plantuml", "json"], 
      "user": "meteorbites"
    }, 
    {
      "alias": "plantuml-code-generator", 
      "repos_name": "plantuml-code-generator", 
      "tags": ["plantuml", "code_generator"], 
      "user": "bafolts"
    }, 
    {
      "alias": "dkd-plantuml", 
      "repos_name": "plantuml", 
      "tags": ["plantuml", "redmine"], 
      "user": "dkd"
    }, 
    {
      "alias": "plantuml-syntax", 
      "repos_name": "plantuml-syntax", 
      "tags": ["plantuml", "vim_plugin"], 
      "user": "aklt"
    }, 
    {
      "alias": "plantuml-server", 
      "repos_name": "plantuml-server", 
      "tags": ["plantuml", "webui"], 
      "user": "plantuml"
    }, 
    {
      "alias": "awesome-flink", 
      "repos_name": "awesome-flink", 
      "tags": ["flink"], 
      "user": "wuchong"
    }, 
    {
      "alias": "awesome-gis", 
      "repos_name": "awesome-gis", 
      "tags": ["gis_awesome"], 
      "user": "sshuair"
    }, 
    {
      "alias": "vscode-plantuml", 
      "repos_name": "vscode-plantuml", 
      "tags": ["plantuml", "vscode_plugin"], 
      "user": "qjebbs"
    }, 
    {
      "user": "apache", 
      "repos_name": "servicemix", 
      "tags": ["servicemix", "asciidoc"]
    }, 
    {
      "user": "hwalsuklee", 
      "repos_name": "awesome-deep-text-detection-recognition", 
      "tags": ["ocr_awesome"]
    }, 
    {
      "user": "ThirtyDegreesRay", 
      "repos_name": "OpenHub", 
      "tags": ["android_app"]
    }, 
    {
      "user": "prisma", 
      "repos_name": "graphql-config", 
      "tags": ["graphql"]
    }, 
    {
      "user": "prisma", 
      "repos_name": "prisma", 
      "tags": ["prisma"]
    }, 
    {
      "user": "catalinmiron", 
      "repos_name": "awesome-prisma", 
      "tags": ["prisma"]
    }, 
    {
      "user": "chentsulin", 
      "repos_name": "awesome-graphql", 
      "tags": ["graphql"]
    }, 
    {
      "user": "jcrygier", 
      "repos_name": "graphql-jpa", 
      "tags": ["graphql_java"]
    }, 
    {
      "user": "graphql-java-kickstart", 
      "repos_name": "graphql-java-tools", 
      "tags": ["graphql_java"]
    }, 
    {
      "user": "graphql-java", 
      "repos_name": "graphql-java", 
      "tags": ["graphql_java"]
    }, 
    {
      "user": "graphql-java", 
      "repos_name": "awesome-graphql-java", 
      "tags": ["graphql_java"]
    }, 
    {
      "user": "graphql-java", 
      "repos_name": "graphql-java-spring", 
      "tags": ["graphql_java"]
    }, 
    {
      "user": "hasura", 
      "repos_name": "awesome-react-graphql", 
      "tags": ["graphql_fe"]
    }, 
    {
      "user": "hasura", 
      "repos_name": "awesome-angular-graphql", 
      "tags": ["graphql_fe"]
    }, 
    {
      "user": "Alejandromndza", 
      "repos_name": "SpringGraphQLMybatis", 
      "tags": ["graphql_java"]
    }, 
    {
      "user": "apollographql", 
      "repos_name": "apollo-client", 
      "tags": ["graphql_fe"]
    }, 
    {
      "user": "brillout", 
      "repos_name": "awesome-angular-components", 
      "tags": ["angular"]
    }
  ]
}
